tests/__init__.py
tests/test_generate_beta_and_proof.py
tests/test_generate_seed_salt_hash.py
tests/test_integration.py
tests/test_new_game.py
tests/test_verify.py
vrf_py/VRF.py
vrf_py/__init__.py
vrf_py/error.py
vrf_py/log.py
vrf-1.0.7.dist-info/METADATA
vrf-1.0.7.dist-info/WHEEL
vrf-1.0.7.dist-info/top_level.txt
vrf-1.0.7.dist-info/RECORD
